{
    "os": "Linux-5.15.0-1064-aws-x86_64-with-glibc2.31",
    "python": "3.10.10",
    "heartbeatAt": "2024-07-29T13:13:43.546249",
    "startedAt": "2024-07-29T13:13:43.274034",
    "docker": null,
    "cuda": null,
    "args": [
        "--enable_logger"
    ],
    "state": "running",
    "program": "/teamspace/studios/this_studio/248716_Luca_Cazzola/LM/part_1/main.py",
    "codePathLocal": "main.py",
    "codePath": "main.py",
    "host": "ip-10-192-15-4",
    "username": "zeus",
    "executable": "/home/zeus/miniconda3/envs/cloudspace/bin/python",
    "cpu_count": 2,
    "cpu_count_logical": 4,
    "cpu_freq": {
        "current": 2400.0,
        "min": 0.0,
        "max": 0.0
    },
    "cpu_freq_per_core": [
        {
            "current": 2400.0,
            "min": 0.0,
            "max": 0.0
        },
        {
            "current": 2400.0,
            "min": 0.0,
            "max": 0.0
        },
        {
            "current": 2400.0,
            "min": 0.0,
            "max": 0.0
        },
        {
            "current": 2400.0,
            "min": 0.0,
            "max": 0.0
        }
    ],
    "disk": {
        "/": {
            "total": 387.4823341369629,
            "used": 34.12690734863281
        }
    },
    "memory": {
        "total": 15.337413787841797
    }
}
